manim_devanagari/__init__.py
manim_devanagari/__main__.py
manim_devanagari-2.0.0.dist-info/LICENSE
manim_devanagari-2.0.0.dist-info/WHEEL
manim_devanagari-2.0.0.dist-info/METADATA
manim_devanagari-2.0.0.dist-info/RECORD
