Metadata-Version: 2.1
Name: manim_devanagari
Version: 2.0.0
Summary: Devanagari plugin for manim
Author-email: AvN Learn <avnlearn@gmail.com>
Classifier: License :: OSI Approved :: MIT License
Requires-Dist: manim
Project-URL: Home, https://github.com/avnlearn/manim-devanagari.git
